gocd_dashboard/__init__.py
gocd_dashboard/__main__.py
gocd_dashboard/app.py
gocd_dashboard/blueprints.py
gocd_dashboard/config.py
gocd_dashboard/gocd.py
gocd_dashboard/utils.py
gocd_dashboard/static/gocd.ico
gocd_dashboard/static/normalize.css
gocd_dashboard/static/style.scss
gocd_dashboard/static/logos/git.png
gocd_dashboard/static/logos/github.png
gocd_dashboard/static/logos/gocd-avatar.png
gocd_dashboard/static/logos/gocd-large.png
gocd_dashboard/static/logos/gocd.png
gocd_dashboard/templates/home.html
gocd_dashboard/templates/pipeline.html
gocd_dashboard-1.0.6.dist-info/DESCRIPTION.rst
gocd_dashboard-1.0.6.dist-info/METADATA
gocd_dashboard-1.0.6.dist-info/RECORD
gocd_dashboard-1.0.6.dist-info/WHEEL
gocd_dashboard-1.0.6.dist-info/entry_points.txt
gocd_dashboard-1.0.6.dist-info/metadata.json
gocd_dashboard-1.0.6.dist-info/top_level.txt
