Metadata-Version: 2.0
Name: gocd-dashboard
Version: 1.0.6
Summary: A dashboard to highlight GoCD pipeline statuses.
Home-page: UNKNOWN
Author: Sam Clements
Author-email: sam.clements@datasift.com
License: None
Platform: UNKNOWN
Classifier: Programming Language :: Python
Classifier: Programming Language :: Python :: 3.3
Requires-Dist: Flask-Gravatar (>=0.4.2)
Requires-Dist: attrs
Requires-Dist: flask (>=0.11.1)
Requires-Dist: requests
Requires-Dist: requests-futures
Provides-Extra: debug
Requires-Dist: flask-debugtoolbar (>=0.10.0); extra == 'debug'
Provides-Extra: deploy
Requires-Dist: gunicorn (>=19.6.0); extra == 'deploy'
